check_lines-0.3.1.data/scripts/check_lines
checklines/files.py
checklines/func.py
checklines/functions.py
checklines/info.py
checklines/main.py
checklines/precommit.py
check_lines-0.3.1.dist-info/LICENSE
check_lines-0.3.1.dist-info/METADATA
check_lines-0.3.1.dist-info/WHEEL
check_lines-0.3.1.dist-info/top_level.txt
check_lines-0.3.1.dist-info/RECORD
