Metadata-Version: 2.1
Name: check-lines
Version: 0.3.1
Summary: A little script to check lines using ctags
Home-page: https://github.com/iRyukizo/check_lines
Author: iRyukizo
Author-email: hugo.moreau@epita.fr
License: MIT
Platform: UNKNOWN
Requires-Python: >=3.5
Requires-Dist: colorama
